digitalsigtool/__init__.py
digitalsigtool/digitalsigtool.py
digitalsigtool-0.1.0.dist-info/LICENSE
digitalsigtool-0.1.0.dist-info/METADATA
digitalsigtool-0.1.0.dist-info/WHEEL
digitalsigtool-0.1.0.dist-info/entry_points.txt
digitalsigtool-0.1.0.dist-info/top_level.txt
digitalsigtool-0.1.0.dist-info/RECORD
