Metadata-Version: 2.1
Name: digitalsigtool
Version: 0.1.0
Summary: A tool to generate and verify digital signatures for files using SHA-256 and a secret key.
Home-page: https://github.com/babaralijamali/digitalsigtool
Author: Babar Ali Jamali
Author-email: babar995@gmail.com
Classifier: Programming Language :: Python :: 3
Classifier: License :: OSI Approved :: MIT License
Classifier: Operating System :: OS Independent
Requires-Python: >=3.6
License-File: LICENSE
